muesr/__init__.py
muesr/settings.py
muesr/core/__init__.py
muesr/core/appdirs.py
muesr/core/atoms.py
muesr/core/cells.py
muesr/core/isstr.py
muesr/core/magmodel.py
muesr/core/ninput.py
muesr/core/nprint.py
muesr/core/parsers.py
muesr/core/prettytable.py
muesr/core/sample.py
muesr/core/sampleErrors.py
muesr/core/spacegroup.dat
muesr/core/spg.py
muesr/engines/__init__.py
muesr/engines/clfc.py
muesr/i_o/__init__.py
muesr/i_o/exportFPS.py
muesr/i_o/sampleIO.py
muesr/i_o/cif/__init__.py
muesr/i_o/cif/cell.py
muesr/i_o/cif/cif.py
muesr/i_o/cif/crystal.py
muesr/i_o/xsf/__init__.py
muesr/i_o/xsf/xsf.py
muesr/i_o/xsf/xsfio.py
muesr/i_o/xsf/xsfrun.py
muesr/tests/__init__.py
muesr/tests/test_muesr.py
muesr/tests/test_settings.py
muesr/tests/core/__init__.py
muesr/tests/core/test_magmodel.py
muesr/tests/core/test_sample.py
muesr/tests/structures/Cd2Os2O7.mcif
muesr/tests/structures/DyFeO3.mcif
muesr/tests/structures/LiFeSO4F.mcif
muesr/tests/structures/ScMnO3.mcif
muesr/tests/structures/crys.xsf
muesr/tests/structures/crys2.xsf
muesr/tests/structures/crys3.xsf
muesr/tests/structures/crys4.xsf
muesr/tests/utilities/__init__.py
muesr/tests/utilities/test_dftgrid.py
muesr/tests/utilities/test_muon.py
muesr/tests/utilities/test_printer.py
muesr/tests/utilities/test_symsearch.py
muesr/utilities/__init__.py
muesr/utilities/dft_grid.py
muesr/utilities/ms.py
muesr/utilities/muon.py
muesr/utilities/printer.py
muesr/utilities/symsearch.py
muesr/utilities/visualize.py
muesr-0.1.2.dist-info/DESCRIPTION.rst
muesr-0.1.2.dist-info/METADATA
muesr-0.1.2.dist-info/RECORD
muesr-0.1.2.dist-info/WHEEL
muesr-0.1.2.dist-info/metadata.json
muesr-0.1.2.dist-info/top_level.txt
