Metadata-Version: 2.0
Name: muesr
Version: 0.1.2
Summary: Magnetic structure and mUon Embedding Site Refinement
Home-page: https://github.com/bonfus/muesr
Author: Pietro Bonfa
Author-email: pietro.bonfa@fis.unipr.it
License: UNKNOWN
Platform: UNKNOWN
Requires-Dist: numpy (>=1.6)
